{
  "version": "1.0",
  "timestamp": "2026-03-22T10:13:21.919Z",
  "phase": "04",
  "phase_name": "learning-analytics",
  "phase_dir": ".planning/phases/04-learning-analytics",
  "plan": 3,
  "task": 0,
  "total_tasks": 0,
  "status": "complete",
  "completed_tasks": [
    {"id": 1, "name": "04-01 Data Layer", "status": "done", "commit": "6368558"},
    {"id": 2, "name": "04-02 Student Analytics UI", "status": "done", "commit": "ab740ba"},
    {"id": 3, "name": "04-03 Teacher Analytics UI", "status": "done", "commit": "73bc98e"},
    {"id": 4, "name": "UAT Testing Phase 04", "status": "done", "commit": "4ad03f5"},
    {"id": 5, "name": "UI Review Phase 04", "status": "done", "commit": "c915b5c"}
  ],
  "remaining_tasks": [],
  "blockers": [],
  "human_actions_pending": [],
  "decisions": [
    {"decision": "fl_chart 0.69.x API — use RadarDataSet/RadarEntry pattern", "rationale": "Latest stable API for radar charts", "phase": "04"},
    {"decision": "DesignColors.surface doesn't exist — use white/moonLight instead", "rationale": "Token not defined in design_tokens.dart", "phase": "04"},
    {"decision": "Top/Bottom performers threshold: >=5.0 → xuất sắc, <5.0 → cần chú ý", "rationale": "Per user requirement — no overlap between lists", "phase": "04"},
    {"decision": "Filter: chips → bottom sheet with time + class filter, removed Học kỳ option", "rationale": "Per user request — simplified filter UX", "phase": "04"},
    {"decision": "ClassOverviewCard: Đã nộp + Nộp muộn + Cao/Thấp nhất in /10 scale", "rationale": "Per UAT fix — all metrics on /10 scale", "phase": "04"},
    {"decision": "UI Review: 22.5/24 (93%) — 4 minor findings", "rationale": "Low priority deviations, production quality approved", "phase": "04"},
    {"decision": "AnalyticsTimeRangeSemester removed from all files", "rationale": "Per user request — removed Học kỳ filter option", "phase": "04"}
  ],
  "uncommitted_files": [],
  "next_action": "/gsd:plan-phase 5 — Plan Phase 05 Personalized Recommendations (REC-01, REC-02, REC-03)",
  "context_notes": "Phase 04 UAT: 8 passed, 0 issues, 5 skipped (data-dependent: Radar chart, Skill mastery, Empty states, Navigation integration need populated submissions data). Flutter analyze: 0 errors, 1 warning (unrelated unnecessary_cast). UI Review committed (22.5/24). Phase 04 COMPLETE. Ready for Phase 05."
}
